nodejs_cmd.py
nodejs_cmd-0.0.1a0.dist-info/LICENSE
nodejs_cmd-0.0.1a0.dist-info/METADATA
nodejs_cmd-0.0.1a0.dist-info/WHEEL
nodejs_cmd-0.0.1a0.dist-info/entry_points.txt
nodejs_cmd-0.0.1a0.dist-info/top_level.txt
nodejs_cmd-0.0.1a0.dist-info/RECORD
