Metadata-Version: 2.1
Name: nodejs-cmd
Version: 0.0.1a0
Summary: Additional Standard Command Line Commands For nodejs-bin
Home-page: https://github.com/samwillis/nodejs-pypi
Author: Sam Willis
License: UNKNOWN
Platform: UNKNOWN
Classifier: License :: OSI Approved :: MIT License
Classifier: Operating System :: OS Independent
Requires-Python: ~=3.5
